<gmd:MD_Metadata xmlns:gco="http://www.isotc211.org/2005/gco" xmlns:gmd="http://www.isotc211.org/2005/gmd" xmlns:gts="http://www.isotc211.org/2005/gts" xmlns:gml="http://www.opengis.net/gml" xmlns:xlink="http://www.w3.org/1999/xlink" xmlns="http://www.isotc211.org/2005/gmd">
  <gmd:fileIdentifier>
    <gco:CharacterString>2d28e0af-c177-628b-d667-22b15b648d55</gco:CharacterString>
  </gmd:fileIdentifier>
  <gmd:language>
    <gco:CharacterString>eng</gco:CharacterString>
  </gmd:language>
  <gmd:characterSet>
    <gmd:MD_CharacterSetCode codeList="http://asdd.ga.gov.au/asdd/profileinfo/gmxCodelists.xml#MD_CharacterSetCode" codeListValue="utf8">utf8</gmd:MD_CharacterSetCode>
  </gmd:characterSet>
  <gmd:hierarchyLevel>
    <gmd:MD_ScopeCode codeList="http://asdd.ga.gov.au/asdd/profileinfo/GAScopeCodeList.xml#MD_ScopeCode" codeListValue="dataset">dataset</gmd:MD_ScopeCode>
  </gmd:hierarchyLevel>
  <gmd:hierarchyLevelName>
    <gco:CharacterString>dataset</gco:CharacterString>
  </gmd:hierarchyLevelName>
  <gmd:contact>
    <gmd:CI_ResponsibleParty>
      <gmd:individualName>
        <gco:CharacterString>omit</gco:CharacterString>
      </gmd:individualName>
      <gmd:organisationName>
        <gco:CharacterString>Toitū Te Whenua Land Information New Zealand</gco:CharacterString>
      </gmd:organisationName>
      <gmd:positionName>
        <gco:CharacterString/>
      </gmd:positionName>
      <gmd:contactInfo>
        <gmd:CI_Contact>
          <gmd:phone>
            <gmd:CI_Telephone>
              <gmd:voice>
                <gco:CharacterString>04 4600110</gco:CharacterString>
              </gmd:voice>
            </gmd:CI_Telephone>
          </gmd:phone>
          <gmd:address>
            <gmd:CI_Address>
              <gmd:deliveryPoint>
                <gco:CharacterString>155 The Terrace</gco:CharacterString>
              </gmd:deliveryPoint>
              <gmd:city>
                <gco:CharacterString>Wellington</gco:CharacterString>
              </gmd:city>
              <gmd:postalCode>
                <gco:CharacterString>6011</gco:CharacterString>
              </gmd:postalCode>
              <gmd:country>
                <gco:CharacterString>New Zealand</gco:CharacterString>
              </gmd:country>
              <gmd:electronicMailAddress>
                <gco:CharacterString>customersupport@linz.govt.nz</gco:CharacterString>
              </gmd:electronicMailAddress>
            </gmd:CI_Address>
          </gmd:address>
        </gmd:CI_Contact>
      </gmd:contactInfo>
      <gmd:role>
        <gmd:CI_RoleCode codeList="http://asdd.ga.gov.au/asdd/profileinfo/gmxCodelists.xml#CI_RoleCode" codeListValue="resourceProvider">resourceProvider</gmd:CI_RoleCode>
      </gmd:role>
    </gmd:CI_ResponsibleParty>
  </gmd:contact>
  <gmd:dateStamp>
    <gco:Date>2023-07-27</gco:Date>
  </gmd:dateStamp>
  <gmd:metadataStandardName>
    <gco:CharacterString>ANZLIC Metadata Profile: An Australian/New Zealand Profile of AS/NZS ISO 19115:2005, Geographic information - Metadata</gco:CharacterString>
  </gmd:metadataStandardName>
  <gmd:metadataStandardVersion>
    <gco:CharacterString>1.1</gco:CharacterString>
  </gmd:metadataStandardVersion>
  <gmd:referenceSystemInfo>
    <gmd:MD_ReferenceSystem>
      <gmd:referenceSystemIdentifier>
        <gmd:RS_Identifier>
          <gmd:code>
            <gco:CharacterString>4167</gco:CharacterString>
          </gmd:code>
        </gmd:RS_Identifier>
      </gmd:referenceSystemIdentifier>
    </gmd:MD_ReferenceSystem>
  </gmd:referenceSystemInfo>
  <gmd:identificationInfo>
    <gmd:MD_DataIdentification>
      <gmd:citation>
        <gmd:CI_Citation>
          <gmd:title>
            <gco:CharacterString>NZ Property Titles</gco:CharacterString>
          </gmd:title>
          <gmd:date>
            <gmd:CI_Date>
              <gmd:date>
                <gco:Date>2011-04</gco:Date>
              </gmd:date>
              <gmd:dateType>
                <gmd:CI_DateTypeCode codeList="http://asdd.ga.gov.au/asdd/profileinfo/gmxCodelists.xml#CI_DateTypeCode" codeListValue="creation">creation</gmd:CI_DateTypeCode>
              </gmd:dateType>
            </gmd:CI_Date>
          </gmd:date>
        </gmd:CI_Citation>
      </gmd:citation>
      <gmd:abstract>
        <gco:CharacterString>This dataset provides title information (excluding ownership) where there is a relationship to one or more primary parcels.

A Record of Title is a record of a property's owners, legal description and the rights and responsibilities  registered against the title.This dataset does not contain any ownership information so that it can be freely distributed. If ownership information is required, you need to [apply for access](https://www.linz.govt.nz/products-services/data/licensing-and-using-data/linz-licence-personal-data).

There can be multiple parcels associated with a title, and a title may only have a part share in a parcel. This means the shape representing the title will be an aggregation of all parcels that the title is associated with. The ‘spatial extents shared’ attribute when equal to ‘false’ will indicate that title has exclusive interest over all of the shape (this will be case for the vast majority).

The originating data for parcel/title associations includes some non-official sources where the official data does not support a link. For more information see the [LINZ website](https://www.linz.govt.nz/products-services/data/types-linz-data/property-ownership-and-boundary-data/types-lds-property-ownership-and-boundary-data)

---
**APIs and web services**
This dataset is available via ArcGIS Online and ArcGIS REST services, as well as our standard APIs.
[LDS APIs and OGC web services](https://data.linz.govt.nz/layer/50804-nz-property-titles/services/)
[ArcGIS Online map services](https://linz.maps.arcgis.com/home/item.html?id=11ba5960f1d7472781310ad93ff2d9c6)</gco:CharacterString>
      </gmd:abstract>
      <gmd:purpose>
        <gco:CharacterString>This layer provides title information (excluding ownership) where there is a data link to one or more primary parcels</gco:CharacterString>
      </gmd:purpose>
      <gmd:status>
        <gmd:MD_ProgressCode codeList="http://asdd.ga.gov.au/asdd/profileinfo/gmxCodelists.xml#MD_ProgressCode" codeListValue="onGoing">onGoing</gmd:MD_ProgressCode>
      </gmd:status>
      <gmd:pointOfContact>
        <gmd:CI_ResponsibleParty>
          <gmd:individualName>
            <gco:CharacterString>Omit</gco:CharacterString>
          </gmd:individualName>
          <gmd:organisationName>
            <gco:CharacterString>Toitū Te Whenua Land Information New Zealand</gco:CharacterString>
          </gmd:organisationName>
          <gmd:positionName>
            <gco:CharacterString>Data Manager - Property Rights</gco:CharacterString>
          </gmd:positionName>
          <gmd:contactInfo>
            <gmd:CI_Contact>
              <gmd:phone>
                <gmd:CI_Telephone>
                  <gmd:voice>
                    <gco:CharacterString>+64 4 460 0110</gco:CharacterString>
                  </gmd:voice>
                  <gmd:facsimile>
                    <gco:CharacterString/>
                  </gmd:facsimile>
                </gmd:CI_Telephone>
              </gmd:phone>
              <gmd:address>
                <gmd:CI_Address>
                  <gmd:deliveryPoint>
                    <gco:CharacterString>155 The Terrace</gco:CharacterString>
                  </gmd:deliveryPoint>
                  <gmd:city>
                    <gco:CharacterString>Wellington</gco:CharacterString>
                  </gmd:city>
                  <gmd:administrativeArea>
                    <gco:CharacterString/>
                  </gmd:administrativeArea>
                  <gmd:postalCode>
                    <gco:CharacterString>6011</gco:CharacterString>
                  </gmd:postalCode>
                  <gmd:country>
                    <gco:CharacterString>New Zealand</gco:CharacterString>
                  </gmd:country>
                  <gmd:electronicMailAddress>
                    <gco:CharacterString>customersupport@linz.govt.nz</gco:CharacterString>
                  </gmd:electronicMailAddress>
                </gmd:CI_Address>
              </gmd:address>
            </gmd:CI_Contact>
          </gmd:contactInfo>
          <gmd:role>
            <gmd:CI_RoleCode codeList="http://asdd.ga.gov.au/asdd/profileinfo/gmxCodelists.xml#CI_RoleCode" codeListValue="pointOfContact">pointOfContact</gmd:CI_RoleCode>
          </gmd:role>
        </gmd:CI_ResponsibleParty>
      </gmd:pointOfContact>
      <gmd:resourceMaintenance>
        <gmd:MD_MaintenanceInformation>
          <gmd:maintenanceAndUpdateFrequency>
            <gmd:MD_MaintenanceFrequencyCode codeList="http://asdd.ga.gov.au/asdd/profileinfo/gmxCodelists.xml#MD_MaintenanceFrequencyCode" codeListValue="weekly">weekly</gmd:MD_MaintenanceFrequencyCode>
          </gmd:maintenanceAndUpdateFrequency>
        </gmd:MD_MaintenanceInformation>
      </gmd:resourceMaintenance>
      <gmd:resourceFormat>
        <gmd:MD_Format>
          <gmd:name>
            <gco:CharacterString>*.xml</gco:CharacterString>
          </gmd:name>
          <gmd:version>
            <gco:CharacterString>Unknown</gco:CharacterString>
          </gmd:version>
        </gmd:MD_Format>
      </gmd:resourceFormat>
      <gmd:descriptiveKeywords>
        <gmd:MD_Keywords>
          <gmd:keyword>
            <gco:CharacterString>New Zealand</gco:CharacterString>
          </gmd:keyword>
          <gmd:type>
            <gmd:MD_KeywordTypeCode codeList="http://asdd.ga.gov.au/asdd/profileinfo/gmxCodelists.xml#MD_KeywordTypeCode" codeListValue="theme">theme</gmd:MD_KeywordTypeCode>
          </gmd:type>
          <gmd:thesaurusName>
            <gmd:CI_Citation>
              <gmd:title>
                <gco:CharacterString>ANZLIC Jurisdictions</gco:CharacterString>
              </gmd:title>
              <gmd:date>
                <gmd:CI_Date>
                  <gmd:date>
                    <gco:Date>2008-10-29</gco:Date>
                  </gmd:date>
                  <gmd:dateType>
                    <gmd:CI_DateTypeCode codeList="http://asdd.ga.gov.au/asdd/profileinfo/gmxCodelists.xml#CI_DateTypeCode" codeListValue="revision">revision</gmd:CI_DateTypeCode>
                  </gmd:dateType>
                </gmd:CI_Date>
              </gmd:date>
              <gmd:edition>
                <gco:CharacterString>Version 2.1</gco:CharacterString>
              </gmd:edition>
              <gmd:editionDate>
                <gco:Date>2008-10-29</gco:Date>
              </gmd:editionDate>
              <gmd:identifier>
                <gmd:MD_Identifier>
                  <gmd:code>
                    <gco:CharacterString>http://asdd.ga.gov.au/asdd/profileinfo/anzlic-jurisdic.xml#anzlic-jurisdic</gco:CharacterString>
                  </gmd:code>
                </gmd:MD_Identifier>
              </gmd:identifier>
              <gmd:citedResponsibleParty>
                <gmd:CI_ResponsibleParty>
                  <gmd:organisationName>
                    <gco:CharacterString>ANZLIC the Spatial Information Council</gco:CharacterString>
                  </gmd:organisationName>
                  <gmd:role>
                    <gmd:CI_RoleCode codeList="http://asdd.ga.gov.au/asdd/profileinfo/gmxCodelists.xml#CI_RoleCode" codeListValue="custodian">custodian</gmd:CI_RoleCode>
                  </gmd:role>
                </gmd:CI_ResponsibleParty>
              </gmd:citedResponsibleParty>
            </gmd:CI_Citation>
          </gmd:thesaurusName>
        </gmd:MD_Keywords>
      </gmd:descriptiveKeywords>
      <gmd:resourceConstraints>
        <gmd:MD_SecurityConstraints>
          <gmd:classification>
            <gmd:MD_ClassificationCode codeList="http://asdd.ga.gov.au/asdd/profileinfo/gmxCodelists.xml#MD_ClassificationCode" codeListValue="unclassified">unclassified</gmd:MD_ClassificationCode>
          </gmd:classification>
        </gmd:MD_SecurityConstraints>
      </gmd:resourceConstraints>
      <gmd:resourceConstraints>
        <gmd:MD_LegalConstraints>
          <gmd:useLimitation>
            <gco:CharacterString>Copyright of this work is owned by Toitū Te Whenua Land Information New Zealand

© LINZ</gco:CharacterString>
          </gmd:useLimitation>
          <gmd:useConstraints>
            <gmd:MD_RestrictionCode codeList="http://asdd.ga.gov.au/asdd/profileinfo/gmxCodelists.xml#MD_RestrictionCode" codeListValue="copyright">copyright</gmd:MD_RestrictionCode>
          </gmd:useConstraints>
        </gmd:MD_LegalConstraints>
      </gmd:resourceConstraints>
      <gmd:resourceConstraints>
        <gmd:MD_LegalConstraints>
          <gmd:useLimitation>
            <gco:CharacterString>Released under Creative Commons Attribution 4.0 International with:

Following Disclaimers:
1. This data is made available through the LINZ Data Service and is based on information contained with Landonline (New Zealand's Official Title and Cadastral System)

2. Not to be used for defining legal parcel boundaries or transacting land




Following Attribution:

"Sourced from the LINZ Data Service and licensed for reuse under CC BY 4.0"

For details see https://www.linz.govt.nz/data/licensing-and-using-data/attributing-linz-data</gco:CharacterString>
          </gmd:useLimitation>
          <gmd:useConstraints>
            <gmd:MD_RestrictionCode codeList="http://asdd.ga.gov.au/asdd/profileinfo/gmxCodelists.xml#MD_RestrictionCode" codeListValue="license">license</gmd:MD_RestrictionCode>
          </gmd:useConstraints>
        </gmd:MD_LegalConstraints>
      </gmd:resourceConstraints>
      <gmd:spatialRepresentationType>
        <gmd:MD_SpatialRepresentationTypeCode codeList="http://asdd.ga.gov.au/asdd/profileinfo/gmxCodelists.xml#MD_SpatialRepresentationTypeCode" codeListValue="vector">vector</gmd:MD_SpatialRepresentationTypeCode>
      </gmd:spatialRepresentationType>
      <gmd:language>
        <gco:CharacterString>eng</gco:CharacterString>
      </gmd:language>
      <gmd:characterSet>
        <gmd:MD_CharacterSetCode codeList="http://asdd.ga.gov.au/asdd/profileinfo/gmxCodelists.xml#MD_CharacterSetCode" codeListValue="utf8">utf8</gmd:MD_CharacterSetCode>
      </gmd:characterSet>
      <gmd:topicCategory>
        <gmd:MD_TopicCategoryCode>boundaries</gmd:MD_TopicCategoryCode>
      </gmd:topicCategory>
      <gmd:topicCategory>
        <gmd:MD_TopicCategoryCode>planningCadastre</gmd:MD_TopicCategoryCode>
      </gmd:topicCategory>
      <gmd:extent>
        <gmd:EX_Extent>
          <gmd:geographicElement>
            <gmd:EX_GeographicBoundingBox>
              <gmd:westBoundLongitude>
                <gco:Decimal>166.688755883</gco:Decimal>
              </gmd:westBoundLongitude>
              <gmd:eastBoundLongitude>
                <gco:Decimal>-175.833301833</gco:Decimal>
              </gmd:eastBoundLongitude>
              <gmd:southBoundLatitude>
                <gco:Decimal>-47.2899925167</gco:Decimal>
              </gmd:southBoundLatitude>
              <gmd:northBoundLatitude>
                <gco:Decimal>-34.12963565</gco:Decimal>
              </gmd:northBoundLatitude>
            </gmd:EX_GeographicBoundingBox>
          </gmd:geographicElement>
        </gmd:EX_Extent>
      </gmd:extent>
      <gmd:extent>
        <gmd:EX_Extent>
          <gmd:geographicElement>
            <gmd:EX_GeographicDescription>
              <gmd:geographicIdentifier>
                <gmd:MD_Identifier>
                  <gmd:authority>
                    <gmd:CI_Citation>
                      <gmd:title>
                        <gco:CharacterString>ANZMet Lite Country codelist</gco:CharacterString>
                      </gmd:title>
                      <gmd:date>
                        <gmd:CI_Date>
                          <gmd:date>
                            <gco:Date>2009-03-31</gco:Date>
                          </gmd:date>
                          <gmd:dateType>
                            <gmd:CI_DateTypeCode codeList="http://asdd.ga.gov.au/asdd/profileinfo/gmxCodelists.xml#CI_DateTypeCode" codeListValue="publication">publication</gmd:CI_DateTypeCode>
                          </gmd:dateType>
                        </gmd:CI_Date>
                      </gmd:date>
                      <gmd:edition>
                        <gco:CharacterString>Version 1.0</gco:CharacterString>
                      </gmd:edition>
                      <gmd:editionDate>
                        <gco:Date>2009-03-31</gco:Date>
                      </gmd:editionDate>
                      <gmd:identifier>
                        <gmd:MD_Identifier>
                          <gmd:code>
                            <gco:CharacterString>http://asdd.ga.gov.au/asdd/profileinfo/anzlic-country.xml#Country</gco:CharacterString>
                          </gmd:code>
                        </gmd:MD_Identifier>
                      </gmd:identifier>
                      <gmd:citedResponsibleParty>
                        <gmd:CI_ResponsibleParty>
                          <gmd:organisationName>
                            <gco:CharacterString>ANZLIC the Spatial Information Council</gco:CharacterString>
                          </gmd:organisationName>
                          <gmd:role>
                            <gmd:CI_RoleCode codeList="http://asdd.ga.gov.au/asdd/profileinfo/gmxCodelists.xml#CI_RoleCode" codeListValue="custodian">custodian</gmd:CI_RoleCode>
                          </gmd:role>
                        </gmd:CI_ResponsibleParty>
                      </gmd:citedResponsibleParty>
                    </gmd:CI_Citation>
                  </gmd:authority>
                  <gmd:code>
                    <gco:CharacterString>nzl</gco:CharacterString>
                  </gmd:code>
                </gmd:MD_Identifier>
              </gmd:geographicIdentifier>
            </gmd:EX_GeographicDescription>
          </gmd:geographicElement>
        </gmd:EX_Extent>
      </gmd:extent>
    </gmd:MD_DataIdentification>
  </gmd:identificationInfo>
  <gmd:distributionInfo>
    <gmd:MD_Distribution>
      <gmd:transferOptions>
        <gmd:MD_DigitalTransferOptions>
          <gmd:onLine>
            <gmd:CI_OnlineResource>
              <gmd:linkage>
                <gmd:URL>https://data.linz.govt.nz/layer/50804-nz-property-titles/</gmd:URL>
              </gmd:linkage>
            </gmd:CI_OnlineResource>
          </gmd:onLine>
        </gmd:MD_DigitalTransferOptions>
      </gmd:transferOptions>
    </gmd:MD_Distribution>
  </gmd:distributionInfo>
  <gmd:dataQualityInfo>
    <gmd:DQ_DataQuality>
      <gmd:scope>
        <gmd:DQ_Scope>
          <gmd:level>
            <gmd:MD_ScopeCode codeList="http://asdd.ga.gov.au/asdd/profileinfo/gmxCodelists.xml#MD_ScopeCode" codeListValue="dataset">dataset</gmd:MD_ScopeCode>
          </gmd:level>
          <gmd:levelDescription>
            <gmd:MD_ScopeDescription>
              <gmd:other>
                <gco:CharacterString>dataset</gco:CharacterString>
              </gmd:other>
            </gmd:MD_ScopeDescription>
          </gmd:levelDescription>
        </gmd:DQ_Scope>
      </gmd:scope>
      <gmd:lineage>
        <gmd:LI_Lineage>
          <gmd:statement>
            <gco:CharacterString>The function of the Registrar-General of Land is to provide a system, whereby the ownership of land can be legally evidenced, under which dealings with it can be effected and recorded.

From the earliest days of colonisation, offices have existed in New Zealand for the registration of instruments affecting land. To enable a record of ownership of land to be kept the Land Registration Ordinance was passed by the Legislative Council of New Zealand on 28th December 1841. This provided for the setting up of Deeds Registry Offices and prescribed the method of registering Crown Grants and other Private Deeds relating to Land. The system is generally known as Deeds Registration System or Deeds System for short.

The Deeds System with modifications continued until the Land Registry Act 1860 was promulgated. After a number of amendments it was replaced by the Land Transfer System (LT Act 1870 and subsequent acts). This is sometimes called the Torrens System, after its originator in South Australia. Since the 1870 all registration takes place under the Land Transfer System. The Land Transfer System provides a simple method of registration and in addition, titles issued under it are guaranteed by the State. The first digital data was created by the Land Titles Office (a division of the Justice Department) in the late 1980s - early 90s. This data formed the electronic land transfer journal and a titles index (Land Title Link). The LTO was amalgamated with DOSLI and finally LINZ. As Landonline was rolled out, the paper titles were converted into digital computer registers. The titles conversion project converted 1.8 million "live" titles and imaged 2 million instruments. Certificate of Titles were replaced by Computer Registers. Both have since been replaced by Record of Title, with the commencement of the Land Transfer Act 2017.</gco:CharacterString>
          </gmd:statement>
        </gmd:LI_Lineage>
      </gmd:lineage>
    </gmd:DQ_DataQuality>
  </gmd:dataQualityInfo>
  <gmd:metadataConstraints>
    <gmd:MD_SecurityConstraints>
      <gmd:classification>
        <gmd:MD_ClassificationCode codeList="http://asdd.ga.gov.au/asdd/profileinfo/gmxCodelists.xml#MD_ClassificationCode" codeListValue="unclassified">unclassified</gmd:MD_ClassificationCode>
      </gmd:classification>
    </gmd:MD_SecurityConstraints>
  </gmd:metadataConstraints>
  <gmd:metadataConstraints>
    <gmd:MD_LegalConstraints>
      <gmd:useLimitation>
        <gco:CharacterString>Copyright of this work is owned by Toitū Te Whenua Land Information New Zealand

© LINZ</gco:CharacterString>
      </gmd:useLimitation>
      <gmd:useConstraints>
        <gmd:MD_RestrictionCode codeList="http://asdd.ga.gov.au/asdd/profileinfo/gmxCodelists.xml#MD_RestrictionCode" codeListValue="copyright">copyright</gmd:MD_RestrictionCode>
      </gmd:useConstraints>
    </gmd:MD_LegalConstraints>
  </gmd:metadataConstraints>
  <gmd:metadataConstraints>
    <gmd:MD_LegalConstraints>
      <gmd:useLimitation>
        <gco:CharacterString>Released by Toitū Te Whenua Land Information New Zealand under Creative Commons Attribution 4.0 International (CC BY 4.0) with:

Following Attribution:

"Sourced from the LINZ Data Service and licensed for reuse under CC BY 4.0"

For details see https://www.linz.govt.nz/data/licensing-and-using-data/attributing-linz-data</gco:CharacterString>
      </gmd:useLimitation>
      <gmd:useConstraints>
        <gmd:MD_RestrictionCode codeList="http://asdd.ga.gov.au/asdd/profileinfo/gmxCodelists.xml#MD_RestrictionCode" codeListValue="license">license</gmd:MD_RestrictionCode>
      </gmd:useConstraints>
    </gmd:MD_LegalConstraints>
  </gmd:metadataConstraints>
</gmd:MD_Metadata>